polarityjam/napari_plugin/__init__.py
polarityjam/napari_plugin/__main__.py
polarityjam/napari_plugin/argument_parsing.py
polarityjam/napari_plugin/startup.py
polarityjam/napari_plugin/model/__init__.py
polarityjam/napari_plugin/model/signals.py
polarityjam/napari_plugin/model/tasks.py
polarityjam/napari_plugin/ui/__init__.py
polarityjam/napari_plugin/ui/napari_pjam_plugin.py
polarityjam/napari_plugin/ui/resources/__init__.py
polarityjam_napari_plugin-0.2.0.dist-info/licenses/LICENSE
polarityjam_napari_plugin-0.2.0.dist-info/METADATA
polarityjam_napari_plugin-0.2.0.dist-info/WHEEL
polarityjam_napari_plugin-0.2.0.dist-info/entry_points.txt
polarityjam_napari_plugin-0.2.0.dist-info/top_level.txt
polarityjam_napari_plugin-0.2.0.dist-info/RECORD
